signs_calculator/__init__.py
signs_calculator/adapters.py
signs_calculator/domain.py
signs_calculator/forms.py
signs_calculator/utils.py
signs_calculator/views.py
signs_calculator/static/signs_calculator/css/main.css
signs_calculator/static/signs_calculator/css/main.css.map
signs_calculator/static/signs_calculator/js/index.js
signs_calculator/static/signs_calculator/scss/main.scss
signs_calculator/static/signs_calculator/scss/base/_reset.scss
signs_calculator/static/signs_calculator/scss/base/_utils.scss
signs_calculator/static/signs_calculator/scss/components/_borders.scss
signs_calculator/static/signs_calculator/scss/components/_buttons.scss
signs_calculator/static/signs_calculator/scss/components/_errors.scss
signs_calculator/static/signs_calculator/scss/components/_forms.scss
signs_calculator/static/signs_calculator/scss/components/_inputs.scss
signs_calculator/static/signs_calculator/scss/helpers/_colors.scss
signs_calculator/static/signs_calculator/scss/pages/_result.scss
signs_calculator/static/signs_calculator/signs_icons/aquarius_big.webp
signs_calculator/static/signs_calculator/signs_icons/aquarius_small.webp
signs_calculator/static/signs_calculator/signs_icons/aries_big.webp
signs_calculator/static/signs_calculator/signs_icons/aries_small.webp
signs_calculator/static/signs_calculator/signs_icons/cancer_big.webp
signs_calculator/static/signs_calculator/signs_icons/cancer_small.webp
signs_calculator/static/signs_calculator/signs_icons/capricorn_big.webp
signs_calculator/static/signs_calculator/signs_icons/capricorn_small.webp
signs_calculator/static/signs_calculator/signs_icons/gemini_big.webp
signs_calculator/static/signs_calculator/signs_icons/gemini_small.webp
signs_calculator/static/signs_calculator/signs_icons/leo_big.webp
signs_calculator/static/signs_calculator/signs_icons/leo_small.webp
signs_calculator/static/signs_calculator/signs_icons/libra_big.webp
signs_calculator/static/signs_calculator/signs_icons/libra_small.webp
flask_signs_calculator-1.2.1.dist-info/METADATA
flask_signs_calculator-1.2.1.dist-info/WHEEL
flask_signs_calculator-1.2.1.dist-info/top_level.txt
flask_signs_calculator-1.2.1.dist-info/RECORD
